athena2pd/__init__.py
athena2pd/core.py
athena2pd/test.py
athena2pd-0.2.1.dist-info/LICENSE
athena2pd-0.2.1.dist-info/METADATA
athena2pd-0.2.1.dist-info/WHEEL
athena2pd-0.2.1.dist-info/top_level.txt
athena2pd-0.2.1.dist-info/RECORD
