Metadata-Version: 2.1
Name: athena2pd
Version: 0.2.1
Summary: Helps simplify the access of databases stored in Amazon Athena by using SQL and pandas DataFrames.
Home-page: https://github.com/joedementri/athena2pd
Author: Joe Dementri
Maintainer: Joe Dementri
Maintainer-email: joedementri42012@gmail.com
License: MIT
Platform: UNKNOWN
Classifier: Development Status :: 3 - Alpha
Classifier: Intended Audience :: Developers
Classifier: Programming Language :: Python :: 2.7
Classifier: Programming Language :: Python :: 3
Classifier: License :: OSI Approved :: MIT License
Classifier: Natural Language :: English
Classifier: Operating System :: OS Independent
Requires-Dist: boto3
Requires-Dist: pandas
